Metadata-Version: 2.1
Name: The-miserable-life-of-architectural-students
Version: 0.0.1
Summary: The miserable life of architectural students pygame
Home-page: https://richiebao.github.io/USDA_CH_final
Author: a9207188
Author-email: a9207188@gmail.com
License: MIT
Platform: any
Requires-Python: >= 3.10.9
